fish/__init__.py
fish/fishml.py
fishml_guess/__init__.py
fishml_me/__init__.py
fishml_guess-0.2.0.dist-info/METADATA
fishml_guess-0.2.0.dist-info/WHEEL
fishml_guess-0.2.0.dist-info/entry_points.txt
fishml_guess-0.2.0.dist-info/top_level.txt
fishml_guess-0.2.0.dist-info/RECORD
