Metadata-Version: 2.1
Name: fishml_guess
Version: 0.2.0
Summary: Default template for PDM package
Author-email: hahahellooo <hahahello777@gmail.com>
License: MIT
Project-URL: Homepage, https://github.com/hahahellooo/hw_fishml
Project-URL: Issues, https://github.com/hahahellooo/hw_fishml/issues
Requires-Python: ==3.11.*
Requires-Dist: numpy>=2.1.1
Requires-Dist: scikit-learn>=1.5.1
Requires-Dist: pytest>=8.3.2
